{   "agents": {   "Alice": {   "goal": [13, 15, 14],
                               "init": [3, 12, 11],
                               "path": []},
                  "Bob": {"goal": [9, 6, 6], "init": [10, 3, 3], "path": []},
                  "Chad": {"goal": [6, 13, 11], "init": [4, 5, 8], "path": []},
                  "Dave": {"goal": [7, 11, 8], "init": [4, 5, 10], "path": []}},
    "config": {   "agent_names": ["Alice", "Bob", "Chad", "Dave"],
                  "count": 30,
                  "edition": "FINAL_2",
                  "env_num": 26,
                  "grid_size": 15,
                  "num_obstacles": 60,
                  "obstacle_size": 1,
                  "seed": 229182293781599497},
    "obstacles": [   {"coords": [5, 7, 13], "size": 1},
                     {"coords": [15, 5, 6], "size": 1},
                     {"coords": [3, 8, 1], "size": 1},
                     {"coords": [5, 14, 14], "size": 1},
                     {"coords": [14, 2, 12], "size": 1},
                     {"coords": [12, 5, 10], "size": 1},
                     {"coords": [12, 8, 14], "size": 1},
                     {"coords": [2, 3, 1], "size": 1},
                     {"coords": [7, 15, 15], "size": 1},
                     {"coords": [3, 6, 2], "size": 1},
                     {"coords": [6, 10, 8], "size": 1},
                     {"coords": [12, 6, 6], "size": 1},
                     {"coords": [15, 7, 8], "size": 1},
                     {"coords": [12, 3, 9], "size": 1},
                     {"coords": [7, 8, 5], "size": 1},
                     {"coords": [6, 9, 9], "size": 1},
                     {"coords": [11, 2, 9], "size": 1},
                     {"coords": [6, 14, 12], "size": 1},
                     {"coords": [4, 1, 7], "size": 1},
                     {"coords": [2, 12, 1], "size": 1},
                     {"coords": [2, 10, 9], "size": 1},
                     {"coords": [8, 8, 4], "size": 1},
                     {"coords": [4, 13, 5], "size": 1},
                     {"coords": [14, 4, 6], "size": 1},
                     {"coords": [1, 2, 5], "size": 1},
                     {"coords": [13, 7, 1], "size": 1},
                     {"coords": [2, 9, 4], "size": 1},
                     {"coords": [12, 1, 7], "size": 1},
                     {"coords": [12, 10, 2], "size": 1},
                     {"coords": [10, 7, 5], "size": 1},
                     {"coords": [3, 11, 1], "size": 1},
                     {"coords": [9, 14, 6], "size": 1},
                     {"coords": [2, 6, 14], "size": 1},
                     {"coords": [15, 3, 5], "size": 1},
                     {"coords": [2, 12, 13], "size": 1},
                     {"coords": [12, 5, 11], "size": 1},
                     {"coords": [10, 11, 13], "size": 1},
                     {"coords": [10, 11, 6], "size": 1},
                     {"coords": [8, 7, 11], "size": 1},
                     {"coords": [11, 1, 5], "size": 1},
                     {"coords": [9, 11, 8], "size": 1},
                     {"coords": [15, 1, 14], "size": 1},
                     {"coords": [13, 3, 6], "size": 1},
                     {"coords": [10, 10, 10], "size": 1},
                     {"coords": [15, 5, 8], "size": 1},
                     {"coords": [10, 10, 9], "size": 1},
                     {"coords": [10, 15, 11], "size": 1},
                     {"coords": [9, 14, 4], "size": 1},
                     {"coords": [5, 4, 10], "size": 1},
                     {"coords": [14, 13, 9], "size": 1},
                     {"coords": [9, 5, 7], "size": 1},
                     {"coords": [6, 12, 5], "size": 1},
                     {"coords": [1, 4, 2], "size": 1},
                     {"coords": [10, 8, 5], "size": 1},
                     {"coords": [15, 1, 15], "size": 1},
                     {"coords": [1, 12, 3], "size": 1},
                     {"coords": [12, 15, 5], "size": 1},
                     {"coords": [10, 5, 8], "size": 1},
                     {"coords": [8, 12, 9], "size": 1},
                     {"coords": [14, 15, 2], "size": 1}]}